<?xml version="1.0" encoding="UTF-8" ?>
<!-- *************************************************************************************
FILE DESCRIPTION
Max Top 5 critical clocks will be reported. For rest user needs to refer to Detailed report
*******************************************************************************************-->
<report_table display_priority="2" name="Timing Summary">
<report_link name="Detailed report">
<data>C:\Users\Phoenix136\Dropbox\FPGA\Microsemi\Nokia5110_Driver_12_1\synthesis\synlog\Driver_Container_fpga_mapper.srr</data>
<title>START OF TIMING REPORT</title>
</report_link>
<row>
<data tcl_name="clock_name">Clock Name</data>
<data tcl_name="req_freq">Req Freq</data>
<data tcl_name="est_freq">Est Freq</data>
<data tcl_name="slack">Slack</data>
</row>
<row>
<data>FCCC_C0_FCCC_C0_0_FCCC|GL0_net_inferred_clock</data>
<data>100.0 MHz</data>
<data>157.8 MHz</data>
<data>3.663</data>
</row>
<row>
<data>timerZ1|timer_clock_out_sig_inferred_clock</data>
<data>100.0 MHz</data>
<data>273.5 MHz</data>
<data>6.344</data>
</row>
<row>
<data>System</data>
<data>100.0 MHz</data>
<data>895.2 MHz</data>
<data>8.883</data>
</row>
</report_table>
